{
  "general_settings": {
    "betaFeatures": false,
    "legacyMode": false,
    "saveBehavior": "addToObsidian",
    "showMoreActionsButton": false,
    "silentOpen": true
  },
  "highlighter_settings": {
    "alwaysShowHighlights": true,
    "highlightBehavior": "highlight-inline",
    "highlighterEnabled": true
  },
  "interpreter_settings": {
    "defaultPromptContext": "",
    "interpreterAutoRun": false,
    "interpreterEnabled": false,
    "interpreterModel": "",
    "models": [],
    "providers": []
  },
  "migrationVersion": 1,
  "property_types": [
    {
      "defaultValue": "{{title}}",
      "name": "title",
      "type": "text"
    },
    {
      "defaultValue": "{{url}}",
      "name": "source",
      "type": "text"
    },
    {
      "defaultValue": "{{author|split:\", \"|wikilink|join}}",
      "name": "author",
      "type": "multitext"
    },
    {
      "defaultValue": "{{published}}",
      "name": "published",
      "type": "date"
    },
    {
      "defaultValue": "{{date}}",
      "name": "created",
      "type": "date"
    },
    {
      "defaultValue": "clippings",
      "name": "tags",
      "type": "multitext"
    }
  ],
  "reader_settings": {
    "fontSize": 1.5,
    "lineHeight": 1.6,
    "maxWidth": 38,
    "theme": "default",
    "themeMode": "auto"
  },
  "stats": {
    "addToObsidian": 9,
    "copyToClipboard": 0,
    "saveFile": 0,
    "share": 0
  },
  "template_174073799192097d7byhi1": {
    "id": "174073799192097d7byhi1",
    "name": "Default",
    "behavior": "create",
    "noteNameFormat": "++ {{title}}",
    "path": "/",
    "noteContentFormat": "\n{{content}}",
    "context": "",
    "properties": [
      {
        "id": "17407379919206pi3e7vlq",
        "name": "source",
        "value": "{{url}}",
        "type": "text"
      },
      {
        "id": "1740737991920b5wjsj0lk",
        "name": "created",
        "value": "{{time}}",
        "type": "date"
      }
    ],
    "triggers": []
  },
  "template_list": [
    "174073799192097d7byhi1"
  ],
  "vaults": []
}